super_mario/__init__.py
super_mario/__main__.py
super_mario/constants.py
super_mario/setup.py
super_mario/tools.py
super_mario/components/__init__.py
super_mario/components/box.py
super_mario/components/brick.py
super_mario/components/coin.py
super_mario/components/enemy.py
super_mario/components/info.py
super_mario/components/player.py
super_mario/components/powerup.py
super_mario/components/stuff.py
super_mario/data/maps/level_1.json
super_mario/data/maps/level_2.json
super_mario/data/maps/level_3.json
super_mario/data/maps/level_4.json
super_mario/data/player/luigi.json
super_mario/data/player/mario.json
super_mario/resources/graphics/enemies.png
super_mario/resources/graphics/item_objects.png
super_mario/resources/graphics/level_1.png
super_mario/resources/graphics/level_2.png
super_mario/resources/graphics/level_3.png
super_mario/resources/graphics/level_4.png
super_mario/resources/graphics/mario_bros.png
super_mario/resources/graphics/smb_enemies_sheet.png
super_mario/resources/graphics/text_images.png
super_mario/resources/graphics/tile_set.png
super_mario/resources/graphics/title_screen.png
super_mario/states/__init__.py
super_mario/states/level.py
super_mario/states/load_screen.py
super_mario/states/main_menu.py
super_mario_game-0.0.1.dist-info/METADATA
super_mario_game-0.0.1.dist-info/WHEEL
super_mario_game-0.0.1.dist-info/entry_points.txt
super_mario_game-0.0.1.dist-info/top_level.txt
super_mario_game-0.0.1.dist-info/RECORD
