Metadata-Version: 2.1
Name: super-mario-game
Version: 0.0.1
Summary: a simple SuperMario game
Author-email: marblexu <47616581+marblexu@users.noreply.github.com>
License: MIT
Project-URL: Homepage, https://github.com/marblexu/PythonSuperMario
Project-URL: Download, https://github.com/marblexu/PythonSuperMario/releases
Project-URL: Bug Report, https://github.com/marblexu/PythonSuperMario/issues
Project-URL: Source, https://github.com/marblexu/PythonSuperMario
Keywords: pygame
Classifier: Development Status :: 3 - Alpha
Classifier: Intended Audience :: Developers
Classifier: Topic :: Software Development :: Build Tools
Classifier: License :: OSI Approved :: GNU General Public License v3 (GPLv3)
Classifier: Operating System :: Microsoft :: Windows
Classifier: Operating System :: POSIX
Classifier: Operating System :: Unix
Classifier: Operating System :: MacOS
Classifier: Programming Language :: Python :: 3 :: Only
Classifier: Programming Language :: Python :: 3
Classifier: Programming Language :: Python :: 3.7
Classifier: Programming Language :: Python :: 3.8
Classifier: Programming Language :: Python :: 3.9
Classifier: Programming Language :: Python :: 3.10
Classifier: Programming Language :: Python :: 3.11
Classifier: Programming Language :: Python :: 3.12
Classifier: Programming Language :: Python :: Implementation :: CPython
Classifier: Programming Language :: Python :: Implementation :: PyPy
Requires-Python: >=3.7
Requires-Dist: pygame >=1.9
